benchq/__init__.py
benchq/timing.py
benchq/visualization_tools.py
benchq/algorithms/__init__.py
benchq/algorithms/profolio_optimization.py
benchq/algorithms/time_evolution.py
benchq/algorithms/data_structures/__init__.py
benchq/algorithms/data_structures/algorithm_implementation.py
benchq/algorithms/data_structures/error_budget.py
benchq/algorithms/data_structures/graph_partition.py
benchq/algorithms/gsee/__init__.py
benchq/algorithms/gsee/ld_gsee.py
benchq/algorithms/gsee/qpe_gsee.py
benchq/compilation/__init__.py
benchq/compilation/graph_sim_data.jl
benchq/compilation/initialize_julia.py
benchq/compilation/jabalizer_wrapper.jl
benchq/compilation/julia_utils.py
benchq/compilation/pyliqtr_transpilation.py
benchq/compilation/rbs_hyperparam_tuning.py
benchq/compilation/ruby_slippers.jl
benchq/compilation/transpile_to_native_gates.py
benchq/conversions/__init__.py
benchq/conversions/_circuit_translations.py
benchq/conversions/_openfermion_pyliqtr.py
benchq/decoder_modeling/__init__.py
benchq/decoder_modeling/decoder.py
benchq/decoder_modeling/decoder_resource_estimator.py
benchq/magic_state_distillation/__init__.py
benchq/magic_state_distillation/autoccz_factories.py
benchq/magic_state_distillation/litinski_factories.py
benchq/magic_state_distillation/magic_state_factory.py
benchq/mlflow/__init__.py
benchq/mlflow/data_logging.py
benchq/problem_embeddings/__init__.py
benchq/problem_embeddings/_qaoa.py
benchq/problem_embeddings/_trotter.py
benchq/problem_embeddings/qpe.py
benchq/problem_embeddings/quantum_program.py
benchq/problem_embeddings/block_encodings/double_factorized_hamiltonian.py
benchq/problem_embeddings/block_encodings/offset_tridiagonal.py
benchq/problem_embeddings/block_encodings/offset_tridiagonal_utils.py
benchq/problem_embeddings/qsp/__init__.py
benchq/problem_embeddings/qsp/_lin_and_dong_qsp.py
benchq/problem_embeddings/qsp/_qsp.py
benchq/problem_embeddings/qsp/get_qsp_phases.py
benchq/problem_embeddings/qsp/get_qsp_polynomial.py
benchq-0.7.0.dist-info/LICENSE
benchq-0.7.0.dist-info/METADATA
benchq-0.7.0.dist-info/WHEEL
benchq-0.7.0.dist-info/top_level.txt
benchq-0.7.0.dist-info/RECORD
