Metadata-Version: 2.1
Name: benchq
Version: 0.7.0
Summary: "BenchQ platform for resource estimation"
Home-page: https://github.com/zapatacomputing/benchq
Author: Zapata Computing Inc.
Author-email: info@zapatacomputing.com,
Classifier: Programming Language :: Python :: 3
Classifier: Operating System :: OS Independent
Classifier: License :: OSI Approved :: Apache Software License
Classifier: Topic :: Scientific/Engineering
Requires-Python: !=3.9.7,>=3.9
License-File: LICENSE
Requires-Dist: orquestra-quantum ==0.12.0
Requires-Dist: orquestra-vqa ==0.9.0
Requires-Dist: orquestra-qiskit ==0.14.0
Requires-Dist: orquestra-cirq ==0.12.0
Requires-Dist: orquestra-opt ==0.10.0
Requires-Dist: networkx >=2.8.7
Requires-Dist: orquestra-sdk[all] >=0.46.0
Requires-Dist: matplotlib >=3.6
Requires-Dist: numpy >=1.20
Requires-Dist: more-itertools ~=9.1.0
Requires-Dist: pandas ==1.5.3
Requires-Dist: pyLIQTR ==0.3.3
Requires-Dist: openfermion[resources] ~=1.6.0
Requires-Dist: pytest
Requires-Dist: graph-state-generation ==0.2.0
Requires-Dist: juliapkg ==0.1.10
Requires-Dist: juliacall ~=0.9.10
Requires-Dist: h5py ~=3.8.0
Requires-Dist: mlflow ~=2.3.2
Requires-Dist: stim ==1.10
Requires-Dist: optuna ==3.3.0
Requires-Dist: cvxpy ==1.3.2
Requires-Dist: aiohttp ~=3.9.0
Requires-Dist: setuptools <=65.6.3
Provides-Extra: azure
Requires-Dist: benchq[pyscf] ; extra == 'azure'
Requires-Dist: azure-quantum ==0.28.262328b1 ; extra == 'azure'
Requires-Dist: pyqir ==0.8.0 ; extra == 'azure'
Requires-Dist: qiskit-qir ==0.3.1 ; extra == 'azure'
Requires-Dist: qiskit-ionq ==0.3.10 ; extra == 'azure'
Provides-Extra: dev
Requires-Dist: orquestra-python-dev ; extra == 'dev'
Requires-Dist: pytest-benchmark ~=4.0.0 ; extra == 'dev'
Requires-Dist: numba ~=0.57.0 ; extra == 'dev'
Requires-Dist: benchq[pyscf] ; extra == 'dev'
Requires-Dist: benchq[azure] ; extra == 'dev'
Requires-Dist: pyright ; extra == 'dev'
Provides-Extra: pyscf
Requires-Dist: pyscf ==2.2.1 ; extra == 'pyscf'
Requires-Dist: scipy <1.11.0 ; extra == 'pyscf'
Requires-Dist: openfermionpyscf ==0.5 ; extra == 'pyscf'
